jtac/__init__.py
jtac/cli.py
jtac/logic.py
jtac-1.0.0.dist-info/AUTHORS.rst
jtac-1.0.0.dist-info/LICENSE
jtac-1.0.0.dist-info/METADATA
jtac-1.0.0.dist-info/WHEEL
jtac-1.0.0.dist-info/entry_points.txt
jtac-1.0.0.dist-info/top_level.txt
jtac-1.0.0.dist-info/RECORD
