Metadata-Version: 2.1
Name: jtac
Version: 1.0.0
Summary: Start, stop and restart your arma servers just with cli
Home-page: https://github.com/corp-0/jtac
Author: Andrés Franco Riquelme Sandoval
Author-email: andresfranco.rs@gmail.com
License: MIT license
Keywords: jtac
Platform: UNKNOWN
Classifier: Development Status :: 2 - Pre-Alpha
Classifier: Intended Audience :: Developers
Classifier: License :: OSI Approved :: MIT License
Classifier: Natural Language :: English
Classifier: Programming Language :: Python :: 3
Classifier: Programming Language :: Python :: 3.4
Classifier: Programming Language :: Python :: 3.5
Classifier: Programming Language :: Python :: 3.6
Classifier: Programming Language :: Python :: 3.7
Requires-Dist: appdirs (==1.4.3)
Requires-Dist: Click (==7.0)
Requires-Dist: pypiwin32
Requires-Dist: six (==1.13.0)
Requires-Dist: WMI (==1.4.9)
